pommes_pre_process/__init__.py
pommes_pre_process/data/areas_temperatures.csv
pommes_pre_process/data/demand.csv
pommes_pre_process/data/ev_areas_demand_profiles.csv
pommes_pre_process/data/ev_calibration_profile.csv
pommes_pre_process/data/ev_fleets.csv
pommes_pre_process/data/test_temp.csv
pommes_pre_process/src/__init__.py
pommes_pre_process/src/aggregation.py
pommes_pre_process/src/ev_demand_model.py
pommes_pre_process/src/temperature.py
pommes_pre_process/src/thermal_sensitivity_model.py
pommes_pre_process/src/utilities.py
pommes_pre_process/tests/__init__.py
pommes_pre_process/tests/test_aggregation_function.py
pommes_pre_process/tests/test_ev_demand_model.py
pommes_pre_process/tests/test_temperature.py
pommes_pre_process/tests/test_thermal_sensitivity_model.py
pommes_pre_process/tests/test_utilities.py
pommes_pre_process-0.1.1.dist-info/LICENCE.txt
pommes_pre_process-0.1.1.dist-info/METADATA
pommes_pre_process-0.1.1.dist-info/WHEEL
pommes_pre_process-0.1.1.dist-info/top_level.txt
pommes_pre_process-0.1.1.dist-info/RECORD
