Metadata-Version: 2.1
Name: pommes-pre-process
Version: 0.1.1
Summary: POMMES pre processing tools
Author-email: Yoann Chiche <yoann.chiche@minesparis.psl.eu>, Yassine Abdelouadoud <yassine.abdelouadoud@minesparis.psl.eu>
Maintainer-email: Yoann Chiche <yoann.chiche@minesparis.psl.eu>, Yassine Abdelouadoud <yassine.abdelouadoud@minesparis.psl.eu>
License: The MIT License (MIT)
Classifier: Development Status :: 3 - Alpha
Classifier: Operating System :: MacOS :: MacOS X
Classifier: Operating System :: Microsoft :: Windows
Classifier: Operating System :: POSIX :: Linux
Classifier: Programming Language :: Python :: 3.10
Classifier: Programming Language :: Python :: 3.11
Classifier: Programming Language :: Python :: 3.12
Classifier: Programming Language :: Python :: 3.13
Classifier: Topic :: Scientific/Engineering :: Physics
Requires-Python: <4.0.0,>=3.10
License-File: LICENCE.txt
Requires-Dist: pandas
Requires-Dist: xarray
